AUTHORS.rst
CONTRIBUTING.rst
HISTORY.rst
LICENSE
MANIFEST.in
README.rst
setup.cfg
setup.py
docs/Makefile
docs/authors.rst
docs/conf.py
docs/contributing.rst
docs/history.rst
docs/index.rst
docs/installation.rst
docs/make.bat
docs/readme.rst
docs/usage.rst
pluckpy/__init__.py
pluckpy/pluckpy.py
pluckpy.egg-info/PKG-INFO
pluckpy.egg-info/SOURCES.txt
pluckpy.egg-info/dependency_links.txt
pluckpy.egg-info/not-zip-safe
pluckpy.egg-info/top_level.txt
tests/__init__.py
tests/test_pluckpy.py