Metadata-Version: 1.1
Name: pluckpy
Version: 0.1.2
Summary: Extract values from a list.
Home-page: https://github.com/shridarpatil/pluckpy
Author: Shridhar Patil
Author-email: shridharpatil2792@gmail.com
License: MIT license
Keywords: pluckpy
Platform: UNKNOWN
Classifier: Development Status :: 2 - Pre-Alpha
Classifier: Intended Audience :: Developers
Classifier: License :: OSI Approved :: MIT License
Classifier: Natural Language :: English
Classifier: Programming Language :: Python :: 2
Classifier: Programming Language :: Python :: 2.6
Classifier: Programming Language :: Python :: 2.7
Classifier: Programming Language :: Python :: 3
Classifier: Programming Language :: Python :: 3.3
Classifier: Programming Language :: Python :: 3.4
Classifier: Programming Language :: Python :: 3.5
